[
  {
    "idLeague": "4328",
    "strLeague": "English Premier League",
    "strSport": "Soccer",
    "strLeagueAlternate": "Premier League, EPL, England"
  },
  {
    "idLeague": "4329",
    "strLeague": "English League Championship",
    "strSport": "Soccer",
    "strLeagueAlternate": "England EFL Championship, English Football League Championship"
  },
  {
    "idLeague": "4330",
    "strLeague": "Scottish Premier League",
    "strSport": "Soccer",
    "strLeagueAlternate": "Scotland Premiership, SPFL, William Hill Premiership"
  },
  {
    "idLeague": "4331",
    "strLeague": "German Bundesliga",
    "strSport": "Soccer",
    "strLeagueAlternate": "Bundesliga, Fußball-Bundesliga"
  },
  {
    "idLeague": "4332",
    "strLeague": "Italian Serie A",
    "strSport": "Soccer",
    "strLeagueAlternate": "Italy Serie A"
  },
  {
    "idLeague": "4334",
    "strLeague": "French Ligue 1",
    "strSport": "Soccer",
    "strLeagueAlternate": "Ligue 1 Conforama France"
  },
  {
    "idLeague": "4335",
    "strLeague": "Spanish La Liga",
    "strSport": "Soccer",
    "strLeagueAlternate": "LaLiga EA Sports, La Liga, Campeonato Nacional de Liga de Primera División"
  },
  {
    "idLeague": "4336",
    "strLeague": "Greek Super League 1",
    "strSport": "Soccer",
    "strLeagueAlternate": "Greek Superleague"
  },
  {
    "idLeague": "4337",
    "strLeague": "Dutch Eredivisie",
    "strSport": "Soccer",
    "strLeagueAlternate": "Eredivisie"
  },
  {
    "idLeague": "4338",
    "strLeague": "Belgian Pro League",
    "strSport": "Soccer",
    "strLeagueAlternate": "Belgium Jupiler Pro League"
  },
  {
    "idLeague": "4339",
    "strLeague": "Turkish Super Lig",
    "strSport": "Soccer",
    "strLeagueAlternate": "Trendyol Süper Lig"
  },
  {
    "idLeague": "4340",
    "strLeague": "Danish Superliga",
    "strSport": "Soccer",
    "strLeagueAlternate": ""
  },
  {
    "idLeague": "4344",
    "strLeague": "Portuguese Primeira Liga",
    "strSport": "Soccer",
    "strLeagueAlternate": "Liga NOS, Liga Portugal Betclic"
  },
  {
    "idLeague": "4346",
    "strLeague": "American Major League Soccer",
    "strSport": "Soccer",
    "strLeagueAlternate": "MLS"
  },
  {
    "idLeague": "4347",
    "strLeague": "Swedish Allsvenskan",
    "strSport": "Soccer",
    "strLeagueAlternate": "Fotbollsallsvenskan"
  },
  {
    "idLeague": "4350",
    "strLeague": "Mexican Primera League",
    "strSport": "Soccer",
    "strLeagueAlternate": "Mexico Liga MX"
  },
  {
    "idLeague": "4351",
    "strLeague": "Brazilian Serie A",
    "strSport": "Soccer",
    "strLeagueAlternate": "Brazil Brasileirão Série A Brasileiro"
  },
  {
    "idLeague": "4354",
    "strLeague": "Ukrainian Premier League",
    "strSport": "Soccer",
    "strLeagueAlternate": "Українська Прем'єр-ліга"
  },
  {
    "idLeague": "4355",
    "strLeague": "Russian Football Premier League",
    "strSport": "Soccer",
    "strLeagueAlternate": "Российская премьер-лига, Rossiyskaya premyer-liga"
  },
  {
    "idLeague": "4356",
    "strLeague": "Australian A-League",
    "strSport": "Soccer",
    "strLeagueAlternate": "A-League"
  },
  {
    "idLeague": "4358",
    "strLeague": "Norwegian Eliteserien",
    "strSport": "Soccer",
    "strLeagueAlternate": "Eliteserien"
  },
  {
    "idLeague": "4359",
    "strLeague": "Chinese Super League",
    "strSport": "Soccer",
    "strLeagueAlternate": "中国足球超级联赛, Zhōngguó Zúqiú Chāojí Liánsài, CSL"
  },
  {
    "idLeague": "4367",
    "strLeague": "_No League",
    "strSport": "Soccer",
    "strLeagueAlternate": ""
  },
  {
    "idLeague": "4370",
    "strLeague": "Formula 1",
    "strSport": "Motorsport",
    "strLeagueAlternate": "F1, Formula One, Formula1, Formula 1, Formula-1"
  },
  {
    "idLeague": "4371",
    "strLeague": "Formula E",
    "strSport": "Motorsport",
    "strLeagueAlternate": "Formula-E, FormulaE"
  },
  {
    "idLeague": "4372",
    "strLeague": "BTCC",
    "strSport": "Motorsport",
    "strLeagueAlternate": "British Touring Car Championship"
  },
  {
    "idLeague": "4373",
    "strLeague": "IndyCar Series",
    "strSport": "Motorsport",
    "strLeagueAlternate": "NTT IndyCar Series"
  },
  {
    "idLeague": "4380",
    "strLeague": "NHL",
    "strSport": "Ice Hockey",
    "strLeagueAlternate": "National Hockey League"
  },
  {
    "idLeague": "4381",
    "strLeague": "UK Elite Ice Hockey League",
    "strSport": "Ice Hockey",
    "strLeagueAlternate": "British Elite League"
  },
  {
    "idLeague": "4387",
    "strLeague": "NBA",
    "strSport": "Basketball",
    "strLeagueAlternate": "National Basketball Association"
  },
  {
    "idLeague": "4388",
    "strLeague": "NBA G League",
    "strSport": "Basketball",
    "strLeagueAlternate": "NBA D League"
  },
  {
    "idLeague": "4391",
    "strLeague": "NFL",
    "strSport": "American Football",
    "strLeagueAlternate": "NFL"
  },
  {
    "idLeague": "4393",
    "strLeague": "NASCAR Cup Series",
    "strSport": "Motorsport",
    "strLeagueAlternate": "NASCAR Sprint Cup Series, NCS"
  },
  {
    "idLeague": "4394",
    "strLeague": "Italian Serie B",
    "strSport": "Soccer",
    "strLeagueAlternate": "Serie B"
  },
  {
    "idLeague": "4395",
    "strLeague": "Scottish Championship",
    "strSport": "Soccer",
    "strLeagueAlternate": "William Hill Championship"
  },
  {
    "idLeague": "4396",
    "strLeague": "English League 1",
    "strSport": "Soccer",
    "strLeagueAlternate": "EFL League One, Sky Bet League One, English Football League One"
  },
  {
    "idLeague": "4397",
    "strLeague": "English League 2",
    "strSport": "Soccer",
    "strLeagueAlternate": "EFL League Two, Sky Bet League Two, English Football League Two"
  },
  {
    "idLeague": "4398",
    "strLeague": "Italian Serie C Girone C",
    "strSport": "Soccer",
    "strLeagueAlternate": "Serie C"
  },
  {
    "idLeague": "4399",
    "strLeague": "German 2. Bundesliga",
    "strSport": "Soccer",
    "strLeagueAlternate": "2. Bundesliga"
  },
  {
    "idLeague": "4400",
    "strLeague": "Spanish La Liga 2",
    "strSport": "Soccer",
    "strLeagueAlternate": "Segunda División, LaLiga SmartBank, LaLiga 123"
  },
  {
    "idLeague": "4401",
    "strLeague": "French Ligue 2",
    "strSport": "Soccer",
    "strLeagueAlternate": "Domino’s Ligue 2, Ligue 2 BKT"
  },
  {
    "idLeague": "4403",
    "strLeague": "Swedish Superettan",
    "strSport": "Soccer",
    "strLeagueAlternate": "Superettan"
  },
  {
    "idLeague": "4404",
    "strLeague": "Brazilian Serie B",
    "strSport": "Soccer",
    "strLeagueAlternate": "Brazilian Brasileirao B Brasileiro"
  },
  {
    "idLeague": "4405",
    "strLeague": "CFL",
    "strSport": "American Football",
    "strLeagueAlternate": ""
  },
  {
    "idLeague": "4406",
    "strLeague": "Argentinian Primera Division",
    "strSport": "Soccer",
    "strLeagueAlternate": "Liga Profesional de Fútbol"
  },
  {
    "idLeague": "4407",
    "strLeague": "MotoGP",
    "strSport": "Motorsport",
    "strLeagueAlternate": ""
  },
  {
    "idLeague": "4408",
    "strLeague": "Spanish Liga ACB",
    "strSport": "Basketball",
    "strLeagueAlternate": "Liga Endesa"
  },
  {
    "idLeague": "4409",
    "strLeague": "WRC",
    "strSport": "Motorsport",
    "strLeagueAlternate": "World Rally Championship"
  },
  {
    "idLeague": "4410",
    "strLeague": "British GT Championship",
    "strSport": "Motorsport",
    "strLeagueAlternate": ""
  },
  {
    "idLeague": "4411",
    "strLeague": "WTCC",
    "strSport": "Motorsport",
    "strLeagueAlternate": "FIA World Touring Car Championship"
  },
  {
    "idLeague": "4412",
    "strLeague": "Super GT series",
    "strSport": "Motorsport",
    "strLeagueAlternate": ""
  },
  {
    "idLeague": "4413",
    "strLeague": "WEC",
    "strSport": "Motorsport",
    "strLeagueAlternate": "FIA World Endurance Championship,FIA WEC"
  },
  {
    "idLeague": "4414",
    "strLeague": "English Prem Rugby",
    "strSport": "Rugby",
    "strLeagueAlternate": "Gallagher Premiership Rugby"
  },
  {
    "idLeague": "4415",
    "strLeague": "English Rugby League Super League",
    "strSport": "Rugby",
    "strLeagueAlternate": ""
  },
  {
    "idLeague": "4416",
    "strLeague": "Australian National Rugby League",
    "strSport": "Rugby",
    "strLeagueAlternate": "NRL"
  },
  {
    "idLeague": "4417",
    "strLeague": "Australian National Rugby Championship",
    "strSport": "Rugby",
    "strLeagueAlternate": ""
  },
  {
    "idLeague": "4419",
    "strLeague": "Swedish Hockey League",
    "strSport": "Ice Hockey",
    "strLeagueAlternate": "SHL"
  },
  {
    "idLeague": "4422",
    "strLeague": "Polish Ekstraklasa",
    "strSport": "Soccer",
    "strLeagueAlternate": "Ekstraklasa, PKO Bank Polski Ekstraklasa"
  },
  {
    "idLeague": "4423",
    "strLeague": "French LNB",
    "strSport": "Basketball",
    "strLeagueAlternate": "LNB"
  },
  {
    "idLeague": "4424",
    "strLeague": "MLB",
    "strSport": "Baseball",
    "strLeagueAlternate": "Major League Baseball"
  },
  {
    "idLeague": "4425",
    "strLeague": "PGA Tour",
    "strSport": "Golf",
    "strLeagueAlternate": ""
  },
  {
    "idLeague": "4426",
    "strLeague": "European Tour",
    "strSport": "Golf",
    "strLeagueAlternate": "European Tour"
  },
  {
    "idLeague": "4427",
    "strLeague": "Can-Am",
    "strSport": "Baseball",
    "strLeagueAlternate": ""
  },
  {
    "idLeague": "4428",
    "strLeague": "Frontier League",
    "strSport": "Baseball",
    "strLeagueAlternate": "Ligue Frontière, LF, FL"
  },
  {
    "idLeague": "4429",
    "strLeague": "FIFA World Cup",
    "strSport": "Soccer",
    "strLeagueAlternate": "World Cup, World Cup Qualifiers"
  },
  {
    "idLeague": "4430",
    "strLeague": "French Top 14",
    "strSport": "Rugby",
    "strLeagueAlternate": ""
  },
  {
    "idLeague": "4431",
    "strLeague": "Super League Basketball",
    "strSport": "Basketball",
    "strLeagueAlternate": "British Basketball League"
  },
  {
    "idLeague": "4432",
    "strLeague": "Uruguayan Primera Division",
    "strSport": "Soccer",
    "strLeagueAlternate": "Liga AUF Uruguaya"
  },
  {
    "idLeague": "4433",
    "strLeague": "Italian Lega Basket",
    "strSport": "Basketball",
    "strLeagueAlternate": "LBA"
  },
  {
    "idLeague": "4434",
    "strLeague": "Australian NBL",
    "strSport": "Basketball",
    "strLeagueAlternate": ""
  },
  {
    "idLeague": "4435",
    "strLeague": "American NASL",
    "strSport": "Soccer",
    "strLeagueAlternate": ""
  },
  {
    "idLeague": "4436",
    "strLeague": "Moto2",
    "strSport": "Motorsport",
    "strLeagueAlternate": ""
  },
  {
    "idLeague": "4437",
    "strLeague": "Moto3",
    "strSport": "Motorsport",
    "strLeagueAlternate": ""
  },
  {
    "idLeague": "4438",
    "strLeague": "DTM",
    "strSport": "Motorsport",
    "strLeagueAlternate": ""
  },
  {
    "idLeague": "4439",
    "strLeague": "GT Series Endurance Cup",
    "strSport": "Motorsport",
    "strLeagueAlternate": " GT World Challenge Europe "
  },
  {
    "idLeague": "4440",
    "strLeague": "GT World Challenge Europe Sprint Cup",
    "strSport": "Motorsport",
    "strLeagueAlternate": "Blancpain GT Series Sprint Cup"
  },
  {
    "idLeague": "4441",
    "strLeague": "German BBL",
    "strSport": "Basketball",
    "strLeagueAlternate": "Basketball Bundesliga"
  },
  {
    "idLeague": "4442",
    "strLeague": "Chinese CBA",
    "strSport": "Basketball",
    "strLeagueAlternate": ""
  },
  {
    "idLeague": "4443",
    "strLeague": "UFC",
    "strSport": "Fighting",
    "strLeagueAlternate": "Ultimate Fighting Championship"
  },
  {
    "idLeague": "4444",
    "strLeague": "WWE",
    "strSport": "Fighting",
    "strLeagueAlternate": "World Wrestling Entertainment, WWF"
  },
  {
    "idLeague": "4445",
    "strLeague": "Boxing",
    "strSport": "Fighting",
    "strLeagueAlternate": ""
  },
  {
    "idLeague": "4446",
    "strLeague": "United Rugby Championship",
    "strSport": "Rugby",
    "strLeagueAlternate": "URC, Pro 14, Pro12, Magners League, Celtic League"
  },
  {
    "idLeague": "4447",
    "strLeague": "Dakar Rally",
    "strSport": "Motorsport",
    "strLeagueAlternate": ""
  },
  {
    "idLeague": "4448",
    "strLeague": "ROH",
    "strSport": "Fighting",
    "strLeagueAlternate": "Ring of Honor"
  },
  {
    "idLeague": "4449",
    "strLeague": "NJPW",
    "strSport": "Fighting",
    "strLeagueAlternate": "New Japan Pro Wrestling"
  },
  {
    "idLeague": "4450",
    "strLeague": "WCW",
    "strSport": "Fighting",
    "strLeagueAlternate": "World Championship Wrestling"
  },
  {
    "idLeague": "4451",
    "strLeague": "ECW",
    "strSport": "Fighting",
    "strLeagueAlternate": "Extreme Championship Wrestling"
  },
  {
    "idLeague": "4452",
    "strLeague": "Greek Basket League",
    "strSport": "Basketball",
    "strLeagueAlternate": ""
  },
  {
    "idLeague": "4453",
    "strLeague": "NWA",
    "strSport": "Fighting",
    "strLeagueAlternate": "National Wrestling Alliance"
  },
  {
    "idLeague": "4454",
    "strLeague": "SBK",
    "strSport": "Motorsport",
    "strLeagueAlternate": " SBK, World Superbike, WSB, WSBK"
  },
  {
    "idLeague": "4455",
    "strLeague": "TNA Wrestling",
    "strSport": "Fighting",
    "strLeagueAlternate": "Impact Wrestling"
  },
  {
    "idLeague": "4456",
    "strLeague": "Australian AFL",
    "strSport": "Australian Football",
    "strLeagueAlternate": "AFL, Australian rules football"
  },
  {
    "idLeague": "4457",
    "strLeague": "Norwegian 1. Divisjon",
    "strSport": "Soccer",
    "strLeagueAlternate": "OBOS-ligaen"
  },
  {
    "idLeague": "4458",
    "strLeague": "English County Championship Division 1",
    "strSport": "Cricket",
    "strLeagueAlternate": "Rothesay County Championship Division 1"
  },
  {
    "idLeague": "4459",
    "strLeague": "English County Championship Division 2",
    "strSport": "Cricket",
    "strLeagueAlternate": ""
  },
  {
    "idLeague": "4460",
    "strLeague": "Indian Premier League",
    "strSport": "Cricket",
    "strLeagueAlternate": "IPL"
  },
  {
    "idLeague": "4461",
    "strLeague": "Australian Big Bash League",
    "strSport": "Cricket",
    "strLeagueAlternate": "KFC Big Bash League"
  },
  {
    "idLeague": "4462",
    "strLeague": "South African T20 Challenge",
    "strSport": "Cricket",
    "strLeagueAlternate": ""
  },
  {
    "idLeague": "4463",
    "strLeague": "English t20 Blast",
    "strSport": "Cricket",
    "strLeagueAlternate": "Twenty20 Cup"
  },
  {
    "idLeague": "4464",
    "strLeague": "ATP World Tour",
    "strSport": "Tennis",
    "strLeagueAlternate": "Association of Tennis Professionals"
  },
  {
    "idLeague": "4465",
    "strLeague": "UCI World Tour",
    "strSport": "Cycling",
    "strLeagueAlternate": ""
  },
  {
    "idLeague": "4466",
    "strLeague": "Electric GT Championship",
    "strSport": "Motorsport",
    "strLeagueAlternate": "Electric GT"
  },
  {
    "idLeague": "4467",
    "strLeague": "Bellator",
    "strSport": "Fighting",
    "strLeagueAlternate": "Bellator Fighting Championships"
  },
  {
    "idLeague": "4468",
    "strLeague": "AMA Supercross Championship",
    "strSport": "Motorsport",
    "strLeagueAlternate": ""
  },
  {
    "idLeague": "4469",
    "strLeague": "Pro Motocross",
    "strSport": "Motorsport",
    "strLeagueAlternate": "AMA Motocross Championship"
  }
]